README.rst
setup.py
mathopt/__init__.py
mathopt/addition_chain.py
mathopt/optimize_terms.py
mathopt.egg-info/PKG-INFO
mathopt.egg-info/SOURCES.txt
mathopt.egg-info/dependency_links.txt
mathopt.egg-info/requires.txt
mathopt.egg-info/top_level.txt
mathopt/David_Wilson_powers/ac0001.txt
mathopt/David_Wilson_powers/ac0002.txt
mathopt/David_Wilson_powers/ac0003.txt
mathopt/David_Wilson_powers/ac0004.txt
mathopt/David_Wilson_powers/ac0005.txt
mathopt/David_Wilson_powers/ac0006.txt
mathopt/David_Wilson_powers/ac0007.txt
mathopt/David_Wilson_powers/ac0008.txt
mathopt/David_Wilson_powers/ac0009.txt
mathopt/David_Wilson_powers/ac0010.txt
mathopt/David_Wilson_powers/ac0011.txt
mathopt/David_Wilson_powers/ac0012.txt
mathopt/David_Wilson_powers/ac0013.txt
mathopt/David_Wilson_powers/ac0014.txt
mathopt/David_Wilson_powers/ac0015.txt
mathopt/David_Wilson_powers/ac0016.txt
mathopt/David_Wilson_powers/ac0017.txt
mathopt/David_Wilson_powers/ac0018.txt
mathopt/David_Wilson_powers/ac0019.txt
mathopt/David_Wilson_powers/ac0020.txt
mathopt/David_Wilson_powers/ac0021.txt
mathopt/David_Wilson_powers/ac0022.txt
mathopt/David_Wilson_powers/ac0023.txt
mathopt/David_Wilson_powers/ac0024.txt
mathopt/David_Wilson_powers/ac0025.txt
mathopt/David_Wilson_powers/ac0026.txt
mathopt/David_Wilson_powers/ac0027.txt
mathopt/David_Wilson_powers/ac0028.txt
mathopt/David_Wilson_powers/ac0029.txt
mathopt/David_Wilson_powers/ac0030.txt
mathopt/David_Wilson_powers/ac0031.txt
mathopt/David_Wilson_powers/ac0032.txt
mathopt/David_Wilson_powers/ac0033.txt
mathopt/David_Wilson_powers/ac0034.txt
mathopt/David_Wilson_powers/ac0035.txt
mathopt/David_Wilson_powers/ac0036.txt
mathopt/David_Wilson_powers/ac0037.txt
mathopt/David_Wilson_powers/ac0038.txt
mathopt/David_Wilson_powers/ac0039.txt
mathopt/David_Wilson_powers/ac0040.txt
mathopt/David_Wilson_powers/ac0041.txt
mathopt/David_Wilson_powers/ac0042.txt
mathopt/David_Wilson_powers/ac0043.txt
mathopt/David_Wilson_powers/ac0044.txt
mathopt/David_Wilson_powers/ac0045.txt
mathopt/David_Wilson_powers/ac0046.txt
mathopt/David_Wilson_powers/ac0047.txt
mathopt/David_Wilson_powers/ac0048.txt
